{
    "memo": "455f5613b5c9937a242bef51595f8b9a923a1ea4ccecdfbf6a203e990998f616",
    "projects": [
        {
            "name": "github.com/alecthomas/template",
            "branch": "master",
            "revision": "a0175ee3bccc567396460bf5acd36800cb10c49c",
            "packages": [
                "."
            ]
        },
        {
            "name": "github.com/alecthomas/units",
            "branch": "master",
            "revision": "2efee857e7cfd4f3d0138cc3cbb1b4966962b93a",
            "packages": [
                "."
            ]
        },
        {
            "name": "github.com/aws/aws-sdk-go",
            "branch": "master",
            "revision": "ab16e115479efb695e122bc4bb3e0ad52419d1ba",
            "packages": [
                "aws",
                "aws/session",
                "service/cloudwatchlogs"
            ]
        },
        {
            "name": "github.com/davecgh/go-spew",
            "version": "v1.1.0",
            "revision": "346938d642f2ec3594ed81d874461961cd0faa76",
            "packages": [
                "spew"
            ]
        },
        {
            "name": "github.com/fatih/color",
            "branch": "master",
            "revision": "7824417a424b65227be8ac9b14d545a7f3e6c3f0",
            "packages": [
                "."
            ]
        },
        {
            "name": "github.com/go-ini/ini",
            "version": "v1.25.2",
            "revision": "74bdc99692c3408cb103221e38675ce8fda0a718",
            "packages": [
                "."
            ]
        },
        {
            "name": "github.com/jmespath/go-jmespath",
            "version": "0.2.2",
            "revision": "3433f3ea46d9f8019119e7dd41274e112a2359a9",
            "packages": [
                "."
            ]
        },
        {
            "name": "github.com/mattn/go-colorable",
            "version": "v0.0.7",
            "revision": "d228849504861217f796da67fae4f6e347643f15",
            "packages": [
                "."
            ]
        },
        {
            "name": "github.com/mattn/go-isatty",
            "branch": "master",
            "revision": "dda3de49cbfcec471bd7a70e6cc01fcc3ff90109",
            "packages": [
                "."
            ]
        },
        {
            "name": "github.com/pmezard/go-difflib",
            "version": "v1.0.0",
            "revision": "792786c7400a136282c1664665ae0a8db921c6c2",
            "packages": [
                "difflib"
            ]
        },
        {
            "name": "github.com/stretchr/testify",
            "version": "v1.1.4",
            "revision": "69483b4bd14f5845b5a1e55bca19e954e827f1d0",
            "packages": [
                "assert"
            ]
        },
        {
            "name": "golang.org/x/sys",
            "branch": "master",
            "revision": "e48874b42435b4347fc52bdee0424a52abc974d7",
            "packages": [
                "unix"
            ]
        },
        {
            "name": "gopkg.in/alecthomas/kingpin.v2",
            "branch": "master",
            "revision": "e9044be3ab2a8e11d4e1f418d12f0790d57e8d70",
            "packages": [
                "."
            ]
        }
    ]
}
